LICENSE
MANIFEST.in
README.rst
setup.py
greenio/__init__.py
greenio/socket.py
greenio.egg-info/PKG-INFO
greenio.egg-info/SOURCES.txt
greenio.egg-info/dependency_links.txt
greenio.egg-info/requires.txt
greenio.egg-info/top_level.txt