Metadata-Version: 1.0
Name: greenio
Version: 0.6.0
Summary: Greenlets for asyncio (PEP 3156).
Home-page: https://github.com/1st1/greenio/
Author: UNKNOWN
Author-email: UNKNOWN
License: Apache 2.0
Platform: UNKNOWN
